generation/__init__.py
generation/data_retrieval.py
generation/manager.py
generation/plot.py
generation/hydro/__init__.py
generation/hydro/data_retrieval.py
generation/hydro/manager.py
generation/hydro/plot.py
generation/hydro/preprocess.py
generation/vres/__init__.py
generation/vres/legacy/__init__.py
generation/vres/legacy/manager.py
generation/vres/legacy/plot.py
generation/vres/legacy/preprocess.py
generation/vres/potentials/__init__.py
generation/vres/potentials/enspreso/__init__.py
generation/vres/potentials/enspreso/manager.py
generation/vres/potentials/enspreso/preprocess.py
generation/vres/potentials/glaes/__init__.py
generation/vres/potentials/glaes/create_priors.py
generation/vres/potentials/glaes/manager.py
generation/vres/potentials/glaes/plot.py
generation/vres/potentials/glaes/preprocess.py
generation/vres/profiles/__init__.py
generation/vres/profiles/data_retrieval.py
generation/vres/profiles/manager.py
generation/vres/profiles/preprocess.py
geographics/__init__.py
geographics/areas.py
geographics/codes.py
geographics/grid_cells.py
geographics/plot.py
geographics/points.py
geographics/shapes.py
indicators/__init__.py
indicators/emissions/__init__.py
indicators/emissions/data_retrieval.py
indicators/emissions/manager.py
indicators/generation/__init__.py
indicators/generation/manager.py
indicators/population/__init__.py
indicators/population/manager.py
load/__init__.py
load/data_retrieval.py
load/info.py
load/manager.py
load/preprocess.py
technologies/__init__.py
technologies/costs.py
technologies/manager.py
topologies/__init__.py
topologies/ehighways.py
topologies/plexos_world.py
topologies/tyndp2018.py
topologies/core/__init__.py
topologies/core/manager.py
topologies/core/plot.py
epippy-0.0.2.dist-info/LICENSE
epippy-0.0.2.dist-info/METADATA
epippy-0.0.2.dist-info/WHEEL
epippy-0.0.2.dist-info/top_level.txt
epippy-0.0.2.dist-info/RECORD
