Metadata-Version: 2.1
Name: epippy
Version: 0.0.2
Summary: Expansion Planning Input Preprocessing in Python
Home-page: https://github.com/montefesp/EPIPPy
Author-email: antoine.dubois@uliege.be
License: MIT
Platform: UNKNOWN
Classifier: Environment :: Console
Classifier: Intended Audience :: Science/Research
Classifier: License :: OSI Approved :: MIT License
Classifier: Natural Language :: English
Classifier: Operating System :: OS Independent
Requires-Python: >=3.7
License-File: LICENSE
Requires-Dist: pypsa
Requires-Dist: gdal (==2.4.4)
Requires-Dist: pycountry
Requires-Dist: geopandas
Requires-Dist: geopy
Requires-Dist: xlrd
Requires-Dist: unidecode
Requires-Dist: dask
Requires-Dist: progressbar2
Requires-Dist: openpyxl
Requires-Dist: geokit
Requires-Dist: glaes
Requires-Dist: windpowerlib
Requires-Dist: vresutils
